<?xml version="1.0" encoding="UTF-8"?>
<Configuration xmlns="http://logging.apache.org/log4j/2.0/config">
    <Appenders>
        <Console name="Console" target="SYSTEM_OUT">
            <PatternLayout
                    pattern="%style{%d{ISO8601}}{black} %highlight{%-5level }[%style{%t}{bright,blue}] %style{%clr{%-40.40c{1.}}}{bright,yellow}: %msg%n%throwable">
            </PatternLayout>
        </Console>
        <RollingFile name="RollingFile"
                     fileName="./logs/spring-boot-logger-log4j2.log"
                     filePattern="./logs/$${date:yyyy-MM}/spring-boot-logger-log4j2-%d{-dd-MMMM-yyyy}-%i.log.gz">
            <PatternLayout>
                <pattern>%d %p %clr{%-40.40c{1.}}{cyan} [%t] %m%n</pattern>
            </PatternLayout>
            <Policies>
                <!-- rollover on startup, daily and when the file reaches
                   10 MegaBytes -->
                <OnStartupTriggeringPolicy/>
                <SizeBasedTriggeringPolicy
                    size="10 MB"/>
                <TimeBasedTriggeringPolicy/>
            </Policies>
        </RollingFile>

        <Async name="AsyncAppender">
            <AppenderRef ref="Console"/>
            <AppenderRef ref="RollingFile"/>
        </Async>

    </Appenders>
    <Loggers>
        <!-- LOG "com.modern.process.web.rest" at TRACE level -->
        <Logger name="com.modern.process.web.rest" level="trace">
            <AppenderRef ref="Console"></AppenderRef>
        </Logger>

        <!-- LOG everything at INFO level -->
        <Root level="info">
            <AppenderRef ref="AsyncAppender"/>
        </Root>
    </Loggers>
</Configuration>